README.md
setup.py
pathflow_mixmatch/__init__.py
pathflow_mixmatch/cli.py
pathflow_mixmatch.egg-info/PKG-INFO
pathflow_mixmatch.egg-info/SOURCES.txt
pathflow_mixmatch.egg-info/dependency_links.txt
pathflow_mixmatch.egg-info/entry_points.txt
pathflow_mixmatch.egg-info/requires.txt
pathflow_mixmatch.egg-info/top_level.txt