Metadata-Version: 2.1
Name: pathflow-mixmatch
Version: 0.1
Summary: Don't mix, match! Simple utilities for improved registration of Histopathology Whole Slide Images.
Home-page: https://github.com/jlevy44/PathFlow-MixMatch
Author: Joshua Levy
Author-email: joshualevy44@berkeley.edu
License: MIT
Platform: UNKNOWN
